Metadata-Version: 2.1
Name: hack4u_69
Version: 0.6.9.1
Summary: Una biblioteca para consultar cursos de hack4u.
Home-page: https://hack4u.io
Author: Marcelo Vazquez
